{
	"0": {
		"name": "A Silly Build Fire",
		"file": "streams/sfx/player/asb_fire.wav"
		},
		
	"1": {
		"name": "Generic Fire",
		"file": "streams/sfx/player/generic_fire.wav"
		},
		
	"2": {
		"name": "Boomerang Loop",
		"file": "streams/sfx/enemy/buma/boomerang.wav"
	},
	"3": {
		"name": "Cow Bell",
		"file": "streams/sfx/cowbell.wav"
		},
		
	"4": {
		"name": "3, 2, 1, Let's Go!",
		"file": "streams/sfx/letsgo.wav"
		},
		
	"5": {
		"name": "Test Vox",
		"file": "streams/sfx/unknown_voice.wav"
	},
	"6": {
		"name": "Generic Accept",
		"file": "streams/sfx/ui/accept.wav"
		},
	"7": {
		"name": "Generic Cancel",
		"file": "streams/sfx/ui/cancel.wav"
		},
	"8": {
		"name": "Generic Select",
		"file": "streams/sfx/ui/select.wav"
		}
}
